SRC/Topsis-Dhriti-102016062.py
Topsis_Dhriti_102016062-1.0.0.dist-info/LICENSE.md
Topsis_Dhriti_102016062-1.0.0.dist-info/METADATA
Topsis_Dhriti_102016062-1.0.0.dist-info/WHEEL
Topsis_Dhriti_102016062-1.0.0.dist-info/top_level.txt
Topsis_Dhriti_102016062-1.0.0.dist-info/RECORD
