Metadata-Version: 2.1
Name: Topsis-Dhriti-102016062
Version: 1.0.0
Summary: A package for topsis score generation.
Author: Dhriti
Author-email: dtaneja_be20@thapar.edu
License: MIT License        
License-File: LICENSE.md
Requires-Dist: pandas
Requires-Dist: numpy
